README.md
setup.cfg
setup.py
examples/__init__.py
examples/hpc_cpu_example.py
examples/pytorch_hpc_example.py
examples/tensorflow_example.py
examples/talk/__init__.py
examples/talk/experiment_integration.py
examples/talk/hopt_integration.py
examples/talk/hopt_integration_hpc.py
test_tube/__init__.py
test_tube/argparse_hopt.py
test_tube/hpc.py
test_tube/hyperopt.py
test_tube/log.py
test_tube.egg-info/PKG-INFO
test_tube.egg-info/SOURCES.txt
test_tube.egg-info/dependency_links.txt
test_tube.egg-info/requires.txt
test_tube.egg-info/top_level.txt
test_tube/hyper_opt_utils/__init__.py
test_tube/hyper_opt_utils/strategies.py