Metadata-Version: 1.1
Name: test-tube
Version: 0.7.3
Summary: Experiment logger and visualizer
Home-page: https://github.com/williamFalcon/test_tube
Author: William Falcon
Author-email: will@hacstudios.com
License: UNKNOWN
Download-URL: https://github.com/williamFalcon/test_tube/archive/0.7.3.tar.gz
Keywords: testing,machine learning,deep learning,prototyping,experimenting,modeling
Platform: UNKNOWN
